django_durable/__init__.py
django_durable/admin.py
django_durable/apps.py
django_durable/engine.py
django_durable/models.py
django_durable/registry.py
django_durable-0.1.1.dist-info/METADATA
django_durable-0.1.1.dist-info/WHEEL
django_durable-0.1.1.dist-info/top_level.txt
django_durable-0.1.1.dist-info/RECORD
