Metadata-Version: 2.4
Name: django-durable
Version: 0.1.1
Summary: Durable execution framework for Django web apps.
Requires-Python: >=3.13
Requires-Dist: django
Provides-Extra: dev
Requires-Dist: pytest~=8.2; extra == "dev"
